py_demo/__init__.py
py_demo/main.py
py_demo/data_files/__init__.py
py_demo/data_files/some_data.txt
py_demo-0.0.2.dist-info/METADATA
py_demo-0.0.2.dist-info/WHEEL
py_demo-0.0.2.dist-info/entry_points.txt
py_demo-0.0.2.dist-info/top_level.txt
py_demo-0.0.2.dist-info/RECORD
