Metadata-Version: 2.1
Name: py-demo
Version: 0.0.2
Summary: Minimal Python Project
Home-page: https://github.com/cfclrk/py-demo
License: UNKNOWN
Project-URL: Source, https://github.com/cfclrk/py-demo
Project-URL: Tracker, https://github.com/cfclrk/py-demo/issues
Platform: UNKNOWN
Requires-Python: >=3.8
Provides-Extra: dev
Requires-Dist: black ; extra == 'dev'
Requires-Dist: flake8 ; extra == 'dev'
Requires-Dist: isort ; extra == 'dev'
Requires-Dist: mypy ; extra == 'dev'
Requires-Dist: pytest ; extra == 'dev'
